elysianfields/__init__.py
elysianfields/fields.py
elysianfields-1.0.5.dist-info/LICENSE
elysianfields-1.0.5.dist-info/METADATA
elysianfields-1.0.5.dist-info/WHEEL
elysianfields-1.0.5.dist-info/top_level.txt
elysianfields-1.0.5.dist-info/RECORD
